haige_py/__init__.py
haige_py/cmdFactory.py
haige_py/Lib/__init__.py
haige_py/Lib/astLib.py
haige_py/Lib/base64Lib.py
haige_py/Lib/pathLib.py
haige_py-2.0.0.dist-info/METADATA
haige_py-2.0.0.dist-info/WHEEL
haige_py-2.0.0.dist-info/top_level.txt
haige_py-2.0.0.dist-info/RECORD
