Metadata-Version: 2.4
Name: haige_py
Version: 2.0.0
Summary: 江湖海哥的常用 python 封装通用包。
Author: 喜欢吃白米饭
Author-email: gzhehai@foxmail.com
Classifier: Programming Language :: Python :: 3
Classifier: License :: OSI Approved :: MIT License
Classifier: Operating System :: OS Independent
Requires-Python: >=3.6
Requires-Dist: astunparse>=1.6.3
Dynamic: author
Dynamic: author-email
Dynamic: classifier
Dynamic: requires-dist
Dynamic: requires-python
Dynamic: summary
